nclustenv/__init__.py
nclustenv/version.py
nclustenv/configs/__init__.py
nclustenv/configs/biclustering/__init__.py
nclustenv/configs/biclustering/binary.py
nclustenv/configs/biclustering/integer.py
nclustenv/configs/biclustering/real.py
nclustenv/configs/triclustering/__init__.py
nclustenv/configs/triclustering/_modules.py
nclustenv/configs/triclustering/binary.py
nclustenv/configs/triclustering/real.py
nclustenv/datasets/__init__.py
nclustenv/datasets/biclustering/__init__.py
nclustenv/datasets/biclustering/binary.py
nclustenv/datasets/biclustering/real.py
nclustenv/datasets/triclustering/__init__.py
nclustenv/datasets/triclustering/binary.py
nclustenv/datasets/triclustering/real.py
nclustenv/environments/__init__.py
nclustenv/environments/registry.py
nclustenv/environments/classic_lr/__init__.py
nclustenv/environments/classic_lr/base.py
nclustenv/environments/classic_lr/biclusterenv.py
nclustenv/environments/classic_lr/triclusterenv.py
nclustenv/utils/__init__.py
nclustenv/utils/actions.py
nclustenv/utils/datasets.py
nclustenv/utils/helper.py
nclustenv/utils/metrics.py
nclustenv/utils/spaces.py
nclustenv/utils/states.py
nclustenv-0.1.0.dist-info/LICENSE.md
nclustenv-0.1.0.dist-info/METADATA
nclustenv-0.1.0.dist-info/WHEEL
nclustenv-0.1.0.dist-info/top_level.txt
nclustenv-0.1.0.dist-info/RECORD
