Metadata-Version: 2.1
Name: nclustenv
Version: 0.1.0
Summary: Gym environments to learn biclustering and triclustering tasks using reinforcement learning.
Home-page: https://github.com/PedroCotovio/nclustenv
Author: Pedro Cotovio
Author-email: pgcotovio@gmail.com
License: GNU GPLv3
Project-URL: Bug Tracker, https://github.com/PedroCotovio/nclustenv/issues
Keywords: biclustring triclustering environment rl gym data nclustenv
Platform: UNKNOWN
Classifier: Programming Language :: Python :: 3.8
Classifier: Programming Language :: Python :: 3.7
Classifier: License :: OSI Approved :: GNU General Public License v3 (GPLv3)
Classifier: Natural Language :: English
Classifier: Operating System :: MacOS :: MacOS X
Classifier: Operating System :: Microsoft :: Windows
Classifier: Operating System :: Unix
Classifier: Intended Audience :: Information Technology
Classifier: Intended Audience :: Science/Research
Classifier: Topic :: Scientific/Engineering :: Artificial Intelligence
Classifier: Topic :: Scientific/Engineering :: Bio-Informatics
Requires-Python: >=3.7
Requires-Dist: nclustgen (>=1.0.3)
Requires-Dist: gym (>=0.18.3)
Requires-Dist: dgl (>=0.6.1)
Requires-Dist: torch (>=1.9.0)
Requires-Dist: inquirer (>=2.7)
Requires-Dist: numpy
Requires-Dist: scipy
